ethon/FasterTg.py
ethon/__init__.py
ethon/mystarts.py
ethon/pyfunc.py
ethon/pyutils.py
ethon/telefunc.py
ethon/teleutils.py
ethon/uploader.py
Tashriethon-0.0.2.dist-info/LICENSE.txt
Tashriethon-0.0.2.dist-info/METADATA
Tashriethon-0.0.2.dist-info/WHEEL
Tashriethon-0.0.2.dist-info/top_level.txt
Tashriethon-0.0.2.dist-info/RECORD
