Metadata-Version: 2.1
Name: Tashriethon
Version: 0.0.2
Summary: Package containing basic functions to build telegram bots.
Home-page: https://github.com/Tashri2342/ethon
Author: Tashri-Code
License: GNU AFFERO GENERAL PUBLIC LICENSE (v3)
Classifier: Programming Language :: Python :: 3
Classifier: Programming Language :: Python :: 3.6
Classifier: Programming Language :: Python :: 3.7
Classifier: Programming Language :: Python :: 3.8
Classifier: Programming Language :: Python :: 3.9
Classifier: License :: OSI Approved :: GNU General Public License v3 (GPLv3)
Classifier: Operating System :: OS Independent
Requires-Python: >=3.6
License-File: LICENSE.txt
Requires-Dist: python-decouple
Requires-Dist: telethon
Requires-Dist: aiofiles
Requires-Dist: aiohttp
Requires-Dist: opencv-python-headless
Requires-Dist: yt-dlp
Requires-Dist: requests
